{
    "nodes": [
        {
            "id": 191669,
            "name": "_INFO-SEM-LIVING-BEING",
            "type": 36,
            "w": 160
        },
        {
            "id": 162761,
            "name": "_INFO-SEM-PERS",
            "type": 36,
            "w": 732
        },
        {
            "id": 217817,
            "name": "_INFO-POLYSEMIC",
            "type": 36,
            "w": 50
        },
        {
            "id": 162759,
            "name": "_INFO-SEM-PLACE",
            "type": 36,
            "w": 504
        },
        {
            "id": 1912917,
            "name": "_INFO-COUNTABLE-YES",
            "type": 36,
            "w": 10
        },
        {
            "id": 50233540,
            "name": "_INFO-WORDREF-YES",
            "type": 36,
            "w": 50
        },
        {
            "id": 162763,
            "name": "_INFO-SEM-THING-CONCRETE",
            "type": 36,
            "w": 1238
        },
        {
            "id": 163012,
            "name": "_INFO-NO-MORE-QUESTION",
            "type": 36,
            "w": 6094
        },
        {
            "id": 191741,
            "name": "_INFO-VOC-COMMON",
            "type": 36,
            "w": 50
        },
        {
            "id": 214534,
            "name": "_INFO-MEANING-FIGURED",
            "type": 36,
            "w": 50
        },
        {
            "id": 223173,
            "name": "_POL-POS",
            "type": 36,
            "w": 50
        },
        {
            "id": 241794,
            "name": "_POL-NEUTRE",
            "type": 36,
            "w": 50
        },
        {
            "id": 248198,
            "name": "_SEX_NO",
            "type": 36,
            "w": 50
        },
        {
            "id": 254876,
            "name": "_POL-POS_PC",
            "type": 36,
            "w": 50
        },
        {
            "id": 254877,
            "name": "_POL-NEUTRE_PC",
            "type": 36,
            "w": 50
        },
        {
            "id": 276096,
            "name": "_INFO-WIKI-YES",
            "type": 36,
            "w": 50
        },
        {
            "id": 317329,
            "name": "_POLIT_7NOPOL",
            "type": 36,
            "w": 50
        },
        {
            "id": 2585996,
            "name": "_INFO-CNRTL-YES",
            "type": 36,
            "w": 50
        },
        {
            "id": 15991431,
            "name": "_PROP-ANIME-YES",
            "type": 36,
            "w": 50
        },
        {
            "id": 15991432,
            "name": "_PROP-ANIME-NO",
            "type": 36,
            "w": 50
        },
        {
            "id": 85068,
            "name": "dictionnaire",
            "type": 1,
            "w": 3493
        }
    ],
    "relations": [
        {
            "id": 666930,
            "node1": 85068,
            "node2": 162759,
            "type": 36,
            "w": 41.0
        },
        {
            "id": 59814646,
            "node1": 85068,
            "node2": 162761,
            "type": 36,
            "w": 40.0
        },
        {
            "id": 2175547,
            "node1": 85068,
            "node2": 162763,
            "type": 36,
            "w": 41.0
        },
        {
            "id": 466505,
            "node1": 85068,
            "node2": 163012,
            "type": 36,
            "w": 51.0
        },
        {
            "id": 60001617,
            "node1": 85068,
            "node2": 191669,
            "type": 36,
            "w": 40.0
        },
        {
            "id": 738664,
            "node1": 85068,
            "node2": 191741,
            "type": 36,
            "w": 44.0
        },
        {
            "id": 52556231,
            "node1": 85068,
            "node2": 214534,
            "type": 36,
            "w": 40.0
        },
        {
            "id": 390220226,
            "node1": 85068,
            "node2": 217817,
            "type": 36,
            "w": 30.0
        },
        {
            "id": 2008860,
            "node1": 85068,
            "node2": 223173,
            "type": 36,
            "w": 450.0
        },
        {
            "id": 2021606,
            "node1": 85068,
            "node2": 241794,
            "type": 36,
            "w": 420.0
        },
        {
            "id": 2190415,
            "node1": 85068,
            "node2": 248198,
            "type": 36,
            "w": 28.0
        },
        {
            "id": 2335850,
            "node1": 85068,
            "node2": 254876,
            "type": 36,
            "w": 52.0
        },
        {
            "id": 2335851,
            "node1": 85068,
            "node2": 254877,
            "type": 36,
            "w": 48.0
        },
        {
            "id": 1177321885,
            "node1": 85068,
            "node2": 276096,
            "type": 36,
            "w": 25.0
        },
        {
            "id": 503469858,
            "node1": 85068,
            "node2": 317329,
            "type": 36,
            "w": 2.13
        },
        {
            "id": 436926414,
            "node1": 85068,
            "node2": 1912917,
            "type": 36,
            "w": 29.0
        },
        {
            "id": 54869901,
            "node1": 85068,
            "node2": 2585996,
            "type": 36,
            "w": 54.0
        },
        {
            "id": 417384156,
            "node1": 85068,
            "node2": 15991431,
            "type": 36,
            "w": 32.0
        },
        {
            "id": 418060958,
            "node1": 85068,
            "node2": 15991432,
            "type": 36,
            "w": 29.0
        },
        {
            "id": 499112544,
            "node1": 85068,
            "node2": 50233540,
            "type": 36,
            "w": 28.0
        }
    ],
    "request": {
        "types_ids": [
            36
        ],
        "not_types_ids": null,
        "min_weight": 1,
        "max_weight": null,
        "start": "2025-12-16T20:35:48.060725",
        "relation_fields": [
            "id",
            "node1",
            "node2",
            "type",
            "w"
        ],
        "node_fields": [
            "id",
            "name",
            "type",
            "w"
        ],
        "without_nodes": false,
        "node1": "dictionnaire",
        "#relations": 20,
        "max_relation_weight": 450.0,
        "#nodes": 21,
        "duration": "0:00:00.009954"
    }
}