{
    "nodes": [
        {
            "id": 94431,
            "name": "neck",
            "type": 1,
            "w": 88
        },
        {
            "id": 94230902,
            "name": "Acide DésoxyriboNucléique",
            "type": 1,
            "w": 47
        },
        {
            "id": 15297314,
            "name": "en:deoxyribose nucleoprotein",
            "type": 1,
            "w": 6
        },
        {
            "id": 240720,
            "name": "squelette>112609",
            "type": 1,
            "w": 202
        },
        {
            "id": 6885693,
            "name": "en:penis",
            "type": 1,
            "w": 25
        },
        {
            "id": 142086,
            "name": "jambe",
            "type": 1,
            "w": 6261
        },
        {
            "id": 221034,
            "name": "bras>112609",
            "type": 1,
            "w": 238
        },
        {
            "id": 12791689,
            "name": "acide désoxyribo-nucléique",
            "type": 1,
            "w": 29
        },
        {
            "id": 95422,
            "name": "cou",
            "type": 1,
            "w": 3550
        },
        {
            "id": 1841061,
            "name": "penile horn",
            "type": 1,
            "w": 25
        },
        {
            "id": 116980,
            "name": "squelette",
            "type": 1,
            "w": 1443
        },
        {
            "id": 6935846,
            "name": "en:dna",
            "type": 1,
            "w": 25
        },
        {
            "id": 39031,
            "name": "cerveau",
            "type": 1,
            "w": 8669
        },
        {
            "id": 109785,
            "name": "peau",
            "type": 1,
            "w": 7466
        },
        {
            "id": 83944,
            "name": "nerf",
            "type": 1,
            "w": 970
        },
        {
            "id": 13451,
            "name": "esprit",
            "type": 1,
            "w": 12729
        },
        {
            "id": 108463,
            "name": "ventre",
            "type": 1,
            "w": 3812
        },
        {
            "id": 16110,
            "name": "bouche",
            "type": 1,
            "w": 8046
        },
        {
            "id": 16747,
            "name": "adn",
            "type": 1,
            "w": 908
        },
        {
            "id": 118203,
            "name": "corps humain",
            "type": 1,
            "w": 632
        },
        {
            "id": 26363,
            "name": "bras",
            "type": 1,
            "w": 11181
        },
        {
            "id": 34898,
            "name": "pied",
            "type": 1,
            "w": 21478
        },
        {
            "id": 225934,
            "name": "oeil>330323",
            "type": 1,
            "w": 296
        },
        {
            "id": 114327,
            "name": "acide désoxyribonucléique",
            "type": 1,
            "w": 214
        },
        {
            "id": 332172,
            "name": "organe sexuel masculin",
            "type": 1,
            "w": 53
        },
        {
            "id": 145953,
            "name": "visage",
            "type": 1,
            "w": 10242
        },
        {
            "id": 139779,
            "name": "ADN",
            "type": 1,
            "w": 2786
        },
        {
            "id": 81934,
            "name": "main",
            "type": 1,
            "w": 40197
        },
        {
            "id": 10850586,
            "name": "corps>112609>49293",
            "type": 1,
            "w": 44
        },
        {
            "id": 3376,
            "name": "membres",
            "type": 1,
            "w": 5108
        },
        {
            "id": 77008,
            "name": "yeux",
            "type": 1,
            "w": 35847
        },
        {
            "id": 144846,
            "name": "tête",
            "type": 1,
            "w": 31430
        },
        {
            "id": 126285,
            "name": "dos",
            "type": 1,
            "w": 5546
        },
        {
            "id": 140715,
            "name": "jambes",
            "type": 1,
            "w": 1747
        },
        {
            "id": 103311,
            "name": "système nerveux",
            "type": 1,
            "w": 1058
        },
        {
            "id": 16828615,
            "name": "PBPs",
            "type": 1,
            "w": 25
        },
        {
            "id": 96211,
            "name": "coeur",
            "type": 1,
            "w": 3623
        },
        {
            "id": 326146,
            "name": "système nerveux en position dorsale",
            "type": 1,
            "w": 56
        },
        {
            "id": 57875,
            "name": "tube digestif",
            "type": 1,
            "w": 196
        },
        {
            "id": 141814,
            "name": "vertèbre",
            "type": 1,
            "w": 450
        },
        {
            "id": 77424,
            "name": "oeil",
            "type": 1,
            "w": 7812
        },
        {
            "id": 74846,
            "name": "corps",
            "type": 1,
            "w": 16266
        },
        {
            "id": 123769,
            "name": "étudiant",
            "type": 1,
            "w": 5544
        },
        {
            "id": 126388,
            "name": "articulation",
            "type": 1,
            "w": 1268
        },
        {
            "id": 233453,
            "name": "cerveau>112609",
            "type": 1,
            "w": 200
        },
        {
            "id": 221019,
            "name": "bouche>112609",
            "type": 1,
            "w": 293
        },
        {
            "id": 1636805,
            "name": "oeil>44335",
            "type": 1,
            "w": 81
        },
        {
            "id": 228289,
            "name": "sexe>218086",
            "type": 1,
            "w": 395
        },
        {
            "id": 60152,
            "name": "bassin",
            "type": 1,
            "w": 3342
        },
        {
            "id": 1841059,
            "name": "Penicillium marneffei",
            "type": 1,
            "w": 25
        },
        {
            "id": 156699,
            "name": "carte d'étudiant",
            "type": 1,
            "w": 58
        },
        {
            "id": 213644,
            "name": "os>116980",
            "type": 1,
            "w": 452
        },
        {
            "id": 14918011,
            "name": "en:DNA",
            "type": 1,
            "w": 6
        },
        {
            "id": 241352,
            "name": "ventre>112609",
            "type": 1,
            "w": 160
        },
        {
            "id": 152844,
            "name": "sang chaud",
            "type": 1,
            "w": 96
        },
        {
            "id": 390927,
            "name": "tête>112609",
            "type": 1,
            "w": 74
        },
        {
            "id": 1841057,
            "name": "pénicilliose",
            "type": 1,
            "w": 25
        },
        {
            "id": 73243,
            "name": "pénil",
            "type": 1,
            "w": 50
        },
        {
            "id": 1667825,
            "name": "partie du corps humain",
            "type": 1,
            "w": 25
        },
        {
            "id": 9939114,
            "name": "en:legs",
            "type": 1,
            "w": 4
        },
        {
            "id": 271734,
            "name": "certificat informatique et internet",
            "type": 1,
            "w": 4
        },
        {
            "id": 34503,
            "name": "pénis",
            "type": 1,
            "w": 1312
        },
        {
            "id": 1779406,
            "name": "mont pubien",
            "type": 1,
            "w": 25
        },
        {
            "id": 27268,
            "name": "examen",
            "type": 1,
            "w": 4268
        },
        {
            "id": 219363,
            "name": "corps>112609",
            "type": 1,
            "w": 243
        },
        {
            "id": 47319,
            "name": "colonne vertébrale",
            "type": 1,
            "w": 451
        },
        {
            "id": 107477,
            "name": "nez",
            "type": 1,
            "w": 4656
        },
        {
            "id": 7015796,
            "name": "en:mons pubis",
            "type": 1,
            "w": 25
        },
        {
            "id": 6798394,
            "name": "en:neck",
            "type": 1,
            "w": 4
        },
        {
            "id": 11008328,
            "name": "ADN>30051",
            "type": 1,
            "w": 65
        },
        {
            "id": 14917526,
            "name": "en:deoxyribonucleic acid",
            "type": 1,
            "w": 4
        },
        {
            "id": 398564,
            "name": "mâchoires",
            "type": 1,
            "w": 69
        },
        {
            "id": 149413,
            "name": "organes",
            "type": 1,
            "w": 3232
        },
        {
            "id": 230305,
            "name": "C2i",
            "type": 666,
            "w": 8
        },
        {
            "id": 230391,
            "name": "c2i",
            "type": 666,
            "w": 4
        },
        {
            "id": 230396,
            "name": "Certificat Informatique et Internet",
            "type": 666,
            "w": 4
        },
        {
            "id": 265621,
            "name": "sac amniotique",
            "type": 1,
            "w": 14
        },
        {
            "id": 213977,
            "name": "bassin>112609",
            "type": 1,
            "w": 32
        }
    ],
    "relations": [
        {
            "id": 982329522,
            "node1": 123769,
            "node2": 3376,
            "type": 9,
            "w": 25.0
        },
        {
            "id": 538373846,
            "node1": 123769,
            "node2": 13451,
            "type": 9,
            "w": 27.0
        },
        {
            "id": 2735515,
            "node1": 123769,
            "node2": 16110,
            "type": 9,
            "w": 39.0
        },
        {
            "id": 14711791,
            "node1": 123769,
            "node2": 16747,
            "type": 9,
            "w": 38.0
        },
        {
            "id": 2719977,
            "node1": 123769,
            "node2": 26363,
            "type": 9,
            "w": 45.0
        },
        {
            "id": 1157936327,
            "node1": 123769,
            "node2": 27268,
            "type": 9,
            "w": 25.0
        },
        {
            "id": 562066228,
            "node1": 123769,
            "node2": 34503,
            "type": 9,
            "w": 31.0
        },
        {
            "id": 2766877,
            "node1": 123769,
            "node2": 34898,
            "type": 9,
            "w": 40.0
        },
        {
            "id": 608081726,
            "node1": 123769,
            "node2": 39031,
            "type": 9,
            "w": 28.0
        },
        {
            "id": 608098265,
            "node1": 123769,
            "node2": 47319,
            "type": 9,
            "w": 26.0
        },
        {
            "id": 608182976,
            "node1": 123769,
            "node2": 57875,
            "type": 9,
            "w": 26.0
        },
        {
            "id": 372365766,
            "node1": 123769,
            "node2": 60152,
            "type": 9,
            "w": 29.0
        },
        {
            "id": 779735749,
            "node1": 123769,
            "node2": 73243,
            "type": 9,
            "w": 25.0
        },
        {
            "id": 2726751,
            "node1": 123769,
            "node2": 74846,
            "type": 9,
            "w": 49.0
        },
        {
            "id": 2682017,
            "node1": 123769,
            "node2": 77008,
            "type": 9,
            "w": 39.0
        },
        {
            "id": 2741305,
            "node1": 123769,
            "node2": 77424,
            "type": 9,
            "w": 42.0
        },
        {
            "id": 2750805,
            "node1": 123769,
            "node2": 81934,
            "type": 9,
            "w": 42.0
        },
        {
            "id": 582595296,
            "node1": 123769,
            "node2": 83944,
            "type": 9,
            "w": 26.0
        },
        {
            "id": 377536754,
            "node1": 123769,
            "node2": 94431,
            "type": 9,
            "w": 31.0
        },
        {
            "id": 2961188,
            "node1": 123769,
            "node2": 95422,
            "type": 9,
            "w": 36.0
        },
        {
            "id": 2774630,
            "node1": 123769,
            "node2": 96211,
            "type": 9,
            "w": 44.0
        },
        {
            "id": 582592627,
            "node1": 123769,
            "node2": 103311,
            "type": 9,
            "w": 26.0
        },
        {
            "id": 2827926,
            "node1": 123769,
            "node2": 107477,
            "type": 9,
            "w": 57.0
        },
        {
            "id": 608177975,
            "node1": 123769,
            "node2": 108463,
            "type": 9,
            "w": 35.0
        },
        {
            "id": 608101144,
            "node1": 123769,
            "node2": 109785,
            "type": 9,
            "w": 27.0
        },
        {
            "id": 15870055,
            "node1": 123769,
            "node2": 114327,
            "type": 9,
            "w": 38.0
        },
        {
            "id": 571397870,
            "node1": 123769,
            "node2": 116980,
            "type": 9,
            "w": 11.0
        },
        {
            "id": 1014603358,
            "node1": 123769,
            "node2": 118203,
            "type": 9,
            "w": 25.0
        },
        {
            "id": 608088345,
            "node1": 123769,
            "node2": 126285,
            "type": 9,
            "w": 26.0
        },
        {
            "id": 608088344,
            "node1": 123769,
            "node2": 126388,
            "type": 9,
            "w": 26.0
        },
        {
            "id": 2890797,
            "node1": 123769,
            "node2": 139779,
            "type": 9,
            "w": 36.0
        },
        {
            "id": 2817659,
            "node1": 123769,
            "node2": 140715,
            "type": 9,
            "w": 44.0
        },
        {
            "id": 608098264,
            "node1": 123769,
            "node2": 141814,
            "type": 9,
            "w": 30.0
        },
        {
            "id": 2754247,
            "node1": 123769,
            "node2": 142086,
            "type": 9,
            "w": 44.0
        },
        {
            "id": 2860025,
            "node1": 123769,
            "node2": 144846,
            "type": 9,
            "w": 44.0
        },
        {
            "id": 2813537,
            "node1": 123769,
            "node2": 145953,
            "type": 9,
            "w": 44.0
        },
        {
            "id": 981303412,
            "node1": 123769,
            "node2": 149413,
            "type": 9,
            "w": 25.0
        },
        {
            "id": 1002456361,
            "node1": 123769,
            "node2": 152844,
            "type": 9,
            "w": 26.0
        },
        {
            "id": 962168814,
            "node1": 123769,
            "node2": 156699,
            "type": 9,
            "w": 29.0
        },
        {
            "id": 608098270,
            "node1": 123769,
            "node2": 213644,
            "type": 9,
            "w": 26.0
        },
        {
            "id": 372495951,
            "node1": 123769,
            "node2": 213977,
            "type": 9,
            "w": 32.0
        },
        {
            "id": 351262704,
            "node1": 123769,
            "node2": 219363,
            "type": 9,
            "w": 33.0
        },
        {
            "id": 2946124,
            "node1": 123769,
            "node2": 221019,
            "type": 9,
            "w": 36.0
        },
        {
            "id": 350892651,
            "node1": 123769,
            "node2": 221034,
            "type": 9,
            "w": 39.0
        },
        {
            "id": 2712795,
            "node1": 123769,
            "node2": 225934,
            "type": 9,
            "w": 45.0
        },
        {
            "id": 3032271,
            "node1": 123769,
            "node2": 228289,
            "type": 9,
            "w": 36.0
        },
        {
            "id": 571396005,
            "node1": 123769,
            "node2": 230305,
            "type": 9,
            "w": 10.0
        },
        {
            "id": 571396006,
            "node1": 123769,
            "node2": 230391,
            "type": 9,
            "w": 10.0
        },
        {
            "id": 571396004,
            "node1": 123769,
            "node2": 230396,
            "type": 9,
            "w": 10.0
        },
        {
            "id": 608081847,
            "node1": 123769,
            "node2": 233453,
            "type": 9,
            "w": 27.0
        },
        {
            "id": 2953215,
            "node1": 123769,
            "node2": 240720,
            "type": 9,
            "w": 36.0
        },
        {
            "id": 608088348,
            "node1": 123769,
            "node2": 241352,
            "type": 9,
            "w": 26.0
        },
        {
            "id": 1007096323,
            "node1": 123769,
            "node2": 265621,
            "type": 9,
            "w": 25.0
        },
        {
            "id": 571396003,
            "node1": 123769,
            "node2": 271734,
            "type": 9,
            "w": 10.0
        },
        {
            "id": 608177988,
            "node1": 123769,
            "node2": 326146,
            "type": 9,
            "w": 26.0
        },
        {
            "id": 561598112,
            "node1": 123769,
            "node2": 332172,
            "type": 9,
            "w": 38.0
        },
        {
            "id": 608182953,
            "node1": 123769,
            "node2": 390927,
            "type": 9,
            "w": 26.0
        },
        {
            "id": 608100919,
            "node1": 123769,
            "node2": 398564,
            "type": 9,
            "w": 35.0
        },
        {
            "id": 25787493,
            "node1": 123769,
            "node2": 1636805,
            "type": 9,
            "w": 45.0
        },
        {
            "id": 981651937,
            "node1": 123769,
            "node2": 1667825,
            "type": 9,
            "w": 25.0
        },
        {
            "id": 781603329,
            "node1": 123769,
            "node2": 1779406,
            "type": 9,
            "w": 25.0
        },
        {
            "id": 780465189,
            "node1": 123769,
            "node2": 1841057,
            "type": 9,
            "w": 25.0
        },
        {
            "id": 1060065460,
            "node1": 123769,
            "node2": 1841059,
            "type": 9,
            "w": 4.0
        },
        {
            "id": 1055069581,
            "node1": 123769,
            "node2": 1841061,
            "type": 9,
            "w": 10.0
        },
        {
            "id": 215794542,
            "node1": 123769,
            "node2": 6798394,
            "type": 9,
            "w": 1.0
        },
        {
            "id": 781221067,
            "node1": 123769,
            "node2": 6885693,
            "type": 9,
            "w": 25.0
        },
        {
            "id": 709661647,
            "node1": 123769,
            "node2": 6935846,
            "type": 9,
            "w": 25.0
        },
        {
            "id": 781356657,
            "node1": 123769,
            "node2": 7015796,
            "type": 9,
            "w": 25.0
        },
        {
            "id": 775491135,
            "node1": 123769,
            "node2": 9939114,
            "type": 9,
            "w": 25.0
        },
        {
            "id": 594515324,
            "node1": 123769,
            "node2": 10850586,
            "type": 9,
            "w": 27.0
        },
        {
            "id": 479126862,
            "node1": 123769,
            "node2": 11008328,
            "type": 9,
            "w": 27.0
        },
        {
            "id": 377729623,
            "node1": 123769,
            "node2": 12791689,
            "type": 9,
            "w": 32.0
        },
        {
            "id": 442193281,
            "node1": 123769,
            "node2": 14917526,
            "type": 9,
            "w": 6.0
        },
        {
            "id": 402648232,
            "node1": 123769,
            "node2": 14918011,
            "type": 9,
            "w": 7.0
        },
        {
            "id": 709821878,
            "node1": 123769,
            "node2": 15297314,
            "type": 9,
            "w": 25.0
        },
        {
            "id": 775578128,
            "node1": 123769,
            "node2": 16828615,
            "type": 9,
            "w": 25.0
        },
        {
            "id": 697262410,
            "node1": 123769,
            "node2": 94230902,
            "type": 9,
            "w": 7.0
        }
    ],
    "request": {
        "types_ids": [
            9
        ],
        "not_types_ids": null,
        "min_weight": 1,
        "max_weight": null,
        "start": "2025-12-14T17:22:36.529123",
        "relation_fields": [
            "id",
            "node1",
            "node2",
            "type",
            "w"
        ],
        "node_fields": [
            "id",
            "name",
            "type",
            "w"
        ],
        "without_nodes": false,
        "node1": "étudiant",
        "#relations": 77,
        "max_relation_weight": 57.0,
        "#nodes": 78,
        "duration": "0:00:00.060163"
    }
}