{
    "nodes": [
        {
            "id": 413329,
            "name": "Espace",
            "type": 1,
            "w": 1195
        },
        {
            "id": 7186991,
            "name": "en:nature",
            "type": 1,
            "w": 25
        },
        {
            "id": 294856208,
            "name": "oeuvre du cinéma",
            "type": 1,
            "w": 36
        },
        {
            "id": 14094383,
            "name": "partie de l'espace",
            "type": 1,
            "w": 28
        },
        {
            "id": 251663,
            "name": "espace>134218",
            "type": 1,
            "w": 41
        },
        {
            "id": 608381,
            "name": "espace>146885",
            "type": 1,
            "w": 25
        },
        {
            "id": 124698178,
            "name": "partie de quelque chose",
            "type": 1,
            "w": 25
        },
        {
            "id": 139575,
            "name": "jardin",
            "type": 1,
            "w": 8724
        },
        {
            "id": 323107,
            "name": "oeuvre>3695",
            "type": 1,
            "w": 51
        },
        {
            "id": 246632,
            "name": "oeuvre de fiction",
            "type": 1,
            "w": 111
        },
        {
            "id": 217201,
            "name": "film>217196",
            "type": 1,
            "w": 1925
        },
        {
            "id": 135190,
            "name": "lieu",
            "type": 1,
            "w": 12888
        },
        {
            "id": 325138,
            "name": "endroit>135190",
            "type": 1,
            "w": 238
        },
        {
            "id": 144938,
            "name": "oeuvre",
            "type": 1,
            "w": 4233
        },
        {
            "id": 22243,
            "name": "pays",
            "type": 1,
            "w": 27351
        },
        {
            "id": 157283,
            "name": "lieu>134218",
            "type": 1,
            "w": 354
        },
        {
            "id": 141387,
            "name": "espace",
            "type": 1,
            "w": 16605
        },
        {
            "id": 3233,
            "name": "partie",
            "type": 1,
            "w": 12287
        },
        {
            "id": 23431,
            "name": "scène",
            "type": 1,
            "w": 9868
        },
        {
            "id": 29592,
            "name": "film",
            "type": 1,
            "w": 12554
        },
        {
            "id": 217196,
            "name": "oeuvre cinématographique",
            "type": 1,
            "w": 103
        },
        {
            "id": 12982269,
            "name": "jardin>34996",
            "type": 1,
            "w": 46
        },
        {
            "id": 330074,
            "name": "espace naturel",
            "type": 1,
            "w": 73
        },
        {
            "id": 35925,
            "name": "terrain",
            "type": 1,
            "w": 7227
        },
        {
            "id": 13991521,
            "name": "la nature",
            "type": 777,
            "w": 122
        },
        {
            "id": 440709,
            "name": "partie de",
            "type": 1,
            "w": 70
        },
        {
            "id": 91343,
            "name": "conception",
            "type": 1,
            "w": 6810
        },
        {
            "id": 2785548,
            "name": "lieu géographique",
            "type": 1,
            "w": 19
        },
        {
            "id": 15800643,
            "name": "revue de vulgarisation",
            "type": 1,
            "w": 25
        },
        {
            "id": 397855,
            "name": "Dame",
            "type": 1,
            "w": 2311
        },
        {
            "id": 15419346,
            "name": "en:Mother Nature",
            "type": 1,
            "w": 25
        },
        {
            "id": 16073002,
            "name": "Espace naturel",
            "type": 1,
            "w": 25
        },
        {
            "id": 2382663,
            "name": "Mère Nature",
            "type": 1,
            "w": 33
        },
        {
            "id": 2412039,
            "name": "Dame Nature",
            "type": 1,
            "w": 25
        },
        {
            "id": 112587,
            "name": "revue",
            "type": 1,
            "w": 4334
        },
        {
            "id": 132390,
            "name": "allégorie",
            "type": 1,
            "w": 280
        },
        {
            "id": 13943,
            "name": "place",
            "type": 1,
            "w": 15901
        },
        {
            "id": 34406,
            "name": "dame",
            "type": 1,
            "w": 4789
        },
        {
            "id": 34996,
            "name": "espace vert",
            "type": 1,
            "w": 383
        },
        {
            "id": 265444485,
            "name": "conception classique",
            "type": 1,
            "w": 85
        },
        {
            "id": 146510,
            "name": "Mère",
            "type": 1,
            "w": 1923
        },
        {
            "id": 330928,
            "name": "champ>141387",
            "type": 1,
            "w": 54
        },
        {
            "id": 132191,
            "name": "Le Grand",
            "type": 1,
            "w": 104
        },
        {
            "id": 238705,
            "name": "comédie dramatique",
            "type": 1,
            "w": 114
        },
        {
            "id": 14936446,
            "name": "en:green space",
            "type": 1,
            "w": 25
        },
        {
            "id": 251735,
            "name": "formation végétale",
            "type": 1,
            "w": 12
        }
    ],
    "relations": [
        {
            "id": 1158695982,
            "node1": 139575,
            "node2": 3233,
            "type": 6,
            "w": 29.0
        },
        {
            "id": 1158695993,
            "node1": 139575,
            "node2": 13943,
            "type": 6,
            "w": 618.91
        },
        {
            "id": 82714052,
            "node1": 139575,
            "node2": 22243,
            "type": 6,
            "w": 321.0
        },
        {
            "id": 9900266,
            "node1": 139575,
            "node2": 23431,
            "type": 6,
            "w": 546.53
        },
        {
            "id": 1158695979,
            "node1": 139575,
            "node2": 29592,
            "type": 6,
            "w": 565.73
        },
        {
            "id": 1158695966,
            "node1": 139575,
            "node2": 34406,
            "type": 6,
            "w": 25.0
        },
        {
            "id": 361456,
            "node1": 139575,
            "node2": 34996,
            "type": 6,
            "w": 70.0
        },
        {
            "id": 9899027,
            "node1": 139575,
            "node2": 35925,
            "type": 6,
            "w": 545.05
        },
        {
            "id": 1158695967,
            "node1": 139575,
            "node2": 91343,
            "type": 6,
            "w": 25.0
        },
        {
            "id": 1158695968,
            "node1": 139575,
            "node2": 112587,
            "type": 6,
            "w": 570.16
        },
        {
            "id": 1158695977,
            "node1": 139575,
            "node2": 132191,
            "type": 6,
            "w": 25.0
        },
        {
            "id": 1158695965,
            "node1": 139575,
            "node2": 132390,
            "type": 6,
            "w": 25.0
        },
        {
            "id": 153348,
            "node1": 139575,
            "node2": 135190,
            "type": 6,
            "w": 305.0
        },
        {
            "id": 1025895545,
            "node1": 139575,
            "node2": 141387,
            "type": 6,
            "w": 63.0
        },
        {
            "id": 1158695973,
            "node1": 139575,
            "node2": 144938,
            "type": 6,
            "w": 35.0
        },
        {
            "id": 1158695971,
            "node1": 139575,
            "node2": 146510,
            "type": 6,
            "w": 31.0
        },
        {
            "id": 331138222,
            "node1": 139575,
            "node2": 157283,
            "type": 6,
            "w": 177.0
        },
        {
            "id": 1158695978,
            "node1": 139575,
            "node2": 217196,
            "type": 6,
            "w": 55.0
        },
        {
            "id": 1158695972,
            "node1": 139575,
            "node2": 217201,
            "type": 6,
            "w": 37.0
        },
        {
            "id": 1158695981,
            "node1": 139575,
            "node2": 238705,
            "type": 6,
            "w": 963.07
        },
        {
            "id": 1158695980,
            "node1": 139575,
            "node2": 246632,
            "type": 6,
            "w": 37.0
        },
        {
            "id": 1158695950,
            "node1": 139575,
            "node2": 251663,
            "type": 6,
            "w": 69.0
        },
        {
            "id": 9919941,
            "node1": 139575,
            "node2": 251735,
            "type": 6,
            "w": 19.0
        },
        {
            "id": 1158695985,
            "node1": 139575,
            "node2": 323107,
            "type": 6,
            "w": 25.0
        },
        {
            "id": 1158695962,
            "node1": 139575,
            "node2": 325138,
            "type": 6,
            "w": 335.0
        },
        {
            "id": 704581165,
            "node1": 139575,
            "node2": 330074,
            "type": 6,
            "w": 107.0
        },
        {
            "id": 1158695994,
            "node1": 139575,
            "node2": 330928,
            "type": 6,
            "w": 25.0
        },
        {
            "id": 1158695969,
            "node1": 139575,
            "node2": 397855,
            "type": 6,
            "w": 37.0
        },
        {
            "id": 1158695970,
            "node1": 139575,
            "node2": 413329,
            "type": 6,
            "w": 25.0
        },
        {
            "id": 1158695995,
            "node1": 139575,
            "node2": 440709,
            "type": 6,
            "w": 31.0
        },
        {
            "id": 1158695963,
            "node1": 139575,
            "node2": 608381,
            "type": 6,
            "w": 581.98
        },
        {
            "id": 705392012,
            "node1": 139575,
            "node2": 2382663,
            "type": 6,
            "w": 107.0
        },
        {
            "id": 929222355,
            "node1": 139575,
            "node2": 2412039,
            "type": 6,
            "w": 114.0
        },
        {
            "id": 659547037,
            "node1": 139575,
            "node2": 2785548,
            "type": 6,
            "w": 339.0
        },
        {
            "id": 704666135,
            "node1": 139575,
            "node2": 7186991,
            "type": 6,
            "w": 111.0
        },
        {
            "id": 1158695955,
            "node1": 139575,
            "node2": 12982269,
            "type": 6,
            "w": 568.69
        },
        {
            "id": 705125492,
            "node1": 139575,
            "node2": 13991521,
            "type": 6,
            "w": 105.0
        },
        {
            "id": 357219567,
            "node1": 139575,
            "node2": 14094383,
            "type": 6,
            "w": 42.0
        },
        {
            "id": 539559275,
            "node1": 139575,
            "node2": 14936446,
            "type": 6,
            "w": 106.0
        },
        {
            "id": 705892707,
            "node1": 139575,
            "node2": 15419346,
            "type": 6,
            "w": 107.0
        },
        {
            "id": 1158695983,
            "node1": 139575,
            "node2": 15800643,
            "type": 6,
            "w": 1000.0
        },
        {
            "id": 704669635,
            "node1": 139575,
            "node2": 16073002,
            "type": 6,
            "w": 111.0
        },
        {
            "id": 1158695964,
            "node1": 139575,
            "node2": 124698178,
            "type": 6,
            "w": 41.0
        },
        {
            "id": 1158695986,
            "node1": 139575,
            "node2": 265444485,
            "type": 6,
            "w": 37.0
        },
        {
            "id": 1158695984,
            "node1": 139575,
            "node2": 294856208,
            "type": 6,
            "w": 55.0
        }
    ],
    "request": {
        "types_ids": [
            6
        ],
        "not_types_ids": null,
        "min_weight": 1,
        "max_weight": null,
        "start": "2025-12-14T17:22:43.073716",
        "relation_fields": [
            "id",
            "node1",
            "node2",
            "type",
            "w"
        ],
        "node_fields": [
            "id",
            "name",
            "type",
            "w"
        ],
        "without_nodes": false,
        "node1": "jardin",
        "#relations": 45,
        "max_relation_weight": 1000.0,
        "#nodes": 46,
        "duration": "0:00:00.056143"
    }
}