{
    "nodes": [
        {
            "id": 250356,
            "name": "trousse>33801>63240",
            "type": 1,
            "w": 50
        },
        {
            "id": 251379,
            "name": "poche revolver",
            "type": 1,
            "w": 8
        },
        {
            "id": 94254,
            "name": "cartable",
            "type": 1,
            "w": 595
        },
        {
            "id": 15236245,
            "name": "en:hand-bag",
            "type": 1,
            "w": 25
        },
        {
            "id": 139906,
            "name": "poche",
            "type": 1,
            "w": 3539
        },
        {
            "id": 293925040,
            "name": "bureau du commissaire",
            "type": 1,
            "w": 0
        },
        {
            "id": 8254,
            "name": "bureau",
            "type": 1,
            "w": 5986
        },
        {
            "id": 42045,
            "name": "étagère",
            "type": 1,
            "w": 597
        },
        {
            "id": 216264,
            "name": "classe>79255>158961",
            "type": 1,
            "w": 20
        },
        {
            "id": 97173,
            "name": "magasin",
            "type": 1,
            "w": 4335
        },
        {
            "id": 15509,
            "name": "stylo",
            "type": 1,
            "w": 2791
        },
        {
            "id": 48825,
            "name": "sac à main",
            "type": 1,
            "w": 483
        },
        {
            "id": 15572034,
            "name": "en:trouser pocket",
            "type": 1,
            "w": 25
        },
        {
            "id": 224082,
            "name": "Université Montpellier II",
            "type": 1,
            "w": 51
        },
        {
            "id": 251448,
            "name": "poche poitrine",
            "type": 1,
            "w": 22
        },
        {
            "id": 40635,
            "name": "sac",
            "type": 1,
            "w": 4080
        },
        {
            "id": 142623,
            "name": "classe",
            "type": 1,
            "w": 7145
        },
        {
            "id": 45179,
            "name": "maison",
            "type": 1,
            "w": 37890
        },
        {
            "id": 15390375,
            "name": "en:back pocket",
            "type": 1,
            "w": 25
        },
        {
            "id": 15048667,
            "name": "en:hip pocket",
            "type": 1,
            "w": 25
        },
        {
            "id": 89591,
            "name": "table",
            "type": 1,
            "w": 8204
        },
        {
            "id": 81934,
            "name": "main",
            "type": 1,
            "w": 40219
        },
        {
            "id": 2469042,
            "name": "poche-revolver",
            "type": 1,
            "w": 25
        },
        {
            "id": 15390374,
            "name": "poche dorsale",
            "type": 1,
            "w": 25
        },
        {
            "id": 251374,
            "name": "poche de pantalon",
            "type": 1,
            "w": 10
        },
        {
            "id": 251375,
            "name": "poche de manteau",
            "type": 1,
            "w": 4
        },
        {
            "id": 91240,
            "name": "école",
            "type": 1,
            "w": 16679
        },
        {
            "id": 263853,
            "name": "sac de femme",
            "type": 1,
            "w": 58
        },
        {
            "id": 14959846,
            "name": "en:handbag",
            "type": 1,
            "w": 25
        },
        {
            "id": 1706487,
            "name": "classe>171870",
            "type": 1,
            "w": 25
        },
        {
            "id": 312716,
            "name": "poche arrière",
            "type": 1,
            "w": 52
        },
        {
            "id": 145427,
            "name": "trousse",
            "type": 1,
            "w": 376
        },
        {
            "id": 250355,
            "name": "trousse>33801",
            "type": 1,
            "w": 10
        },
        {
            "id": 1706488,
            "name": "classe>171869",
            "type": 1,
            "w": 25
        },
        {
            "id": 216261,
            "name": "classe>79255",
            "type": 1,
            "w": 122
        },
        {
            "id": 162529327,
            "name": "Sac à main",
            "type": 1,
            "w": 29
        },
        {
            "id": 52232,
            "name": "tiroir",
            "type": 1,
            "w": 721
        },
        {
            "id": 63999,
            "name": "sacoche",
            "type": 1,
            "w": 227
        }
    ],
    "relations": [
        {
            "id": 174763,
            "node1": 15509,
            "node2": 8254,
            "type": 15,
            "w": 227.0
        },
        {
            "id": 178983,
            "node1": 15509,
            "node2": 40635,
            "type": 15,
            "w": 158.0
        },
        {
            "id": 253548678,
            "node1": 15509,
            "node2": 42045,
            "type": 15,
            "w": 4.0
        },
        {
            "id": 216309,
            "node1": 15509,
            "node2": 45179,
            "type": 15,
            "w": 78.0
        },
        {
            "id": 1467017,
            "node1": 15509,
            "node2": 48825,
            "type": 15,
            "w": 618.0
        },
        {
            "id": 11356376,
            "node1": 15509,
            "node2": 52232,
            "type": 15,
            "w": 49.0
        },
        {
            "id": 256521,
            "node1": 15509,
            "node2": 63999,
            "type": 15,
            "w": 78.0
        },
        {
            "id": 2449583,
            "node1": 15509,
            "node2": 81934,
            "type": 15,
            "w": 79.0
        },
        {
            "id": 1467018,
            "node1": 15509,
            "node2": 89591,
            "type": 15,
            "w": 88.0
        },
        {
            "id": 213830,
            "node1": 15509,
            "node2": 91240,
            "type": 15,
            "w": 108.0
        },
        {
            "id": 174764,
            "node1": 15509,
            "node2": 94254,
            "type": 15,
            "w": 148.0
        },
        {
            "id": 178982,
            "node1": 15509,
            "node2": 97173,
            "type": 15,
            "w": 78.0
        },
        {
            "id": 432603,
            "node1": 15509,
            "node2": 139906,
            "type": 15,
            "w": 108.0
        },
        {
            "id": 104950673,
            "node1": 15509,
            "node2": 142623,
            "type": 15,
            "w": 7.0
        },
        {
            "id": 174766,
            "node1": 15509,
            "node2": 145427,
            "type": 15,
            "w": 226.0
        },
        {
            "id": 104956515,
            "node1": 15509,
            "node2": 216261,
            "type": 15,
            "w": 6.0
        },
        {
            "id": 11354323,
            "node1": 15509,
            "node2": 216264,
            "type": 15,
            "w": 48.0
        },
        {
            "id": 22899007,
            "node1": 15509,
            "node2": 224082,
            "type": 15,
            "w": 42.0
        },
        {
            "id": 104956089,
            "node1": 15509,
            "node2": 250355,
            "type": 15,
            "w": 27.0
        },
        {
            "id": 11354008,
            "node1": 15509,
            "node2": 250356,
            "type": 15,
            "w": 63.0
        },
        {
            "id": 11351573,
            "node1": 15509,
            "node2": 251374,
            "type": 15,
            "w": 48.0
        },
        {
            "id": 11351580,
            "node1": 15509,
            "node2": 251375,
            "type": 15,
            "w": 48.0
        },
        {
            "id": 11351622,
            "node1": 15509,
            "node2": 251379,
            "type": 15,
            "w": 48.0
        },
        {
            "id": 11351427,
            "node1": 15509,
            "node2": 251448,
            "type": 15,
            "w": 48.0
        },
        {
            "id": 539104969,
            "node1": 15509,
            "node2": 263853,
            "type": 15,
            "w": 35.0
        },
        {
            "id": 824752992,
            "node1": 15509,
            "node2": 312716,
            "type": 15,
            "w": 2.0
        },
        {
            "id": 474311993,
            "node1": 15509,
            "node2": 1706487,
            "type": 15,
            "w": 30.0
        },
        {
            "id": 474311989,
            "node1": 15509,
            "node2": 1706488,
            "type": 15,
            "w": 35.0
        },
        {
            "id": 498898855,
            "node1": 15509,
            "node2": 2469042,
            "type": 15,
            "w": 37.0
        },
        {
            "id": 514807754,
            "node1": 15509,
            "node2": 14959846,
            "type": 15,
            "w": 35.0
        },
        {
            "id": 498898838,
            "node1": 15509,
            "node2": 15048667,
            "type": 15,
            "w": 39.0
        },
        {
            "id": 738407490,
            "node1": 15509,
            "node2": 15236245,
            "type": 15,
            "w": 3.0
        },
        {
            "id": 926899498,
            "node1": 15509,
            "node2": 15390374,
            "type": 15,
            "w": 9.0
        },
        {
            "id": 498898825,
            "node1": 15509,
            "node2": 15390375,
            "type": 15,
            "w": 40.0
        },
        {
            "id": 765165594,
            "node1": 15509,
            "node2": 15572034,
            "type": 15,
            "w": 10.0
        },
        {
            "id": 1066406676,
            "node1": 15509,
            "node2": 162529327,
            "type": 15,
            "w": 1.0
        },
        {
            "id": 766142412,
            "node1": 15509,
            "node2": 293925040,
            "type": 15,
            "w": 27.0
        }
    ],
    "request": {
        "types_ids": [
            15
        ],
        "not_types_ids": null,
        "min_weight": 1,
        "max_weight": null,
        "start": "2025-12-16T22:43:02.772626",
        "relation_fields": [
            "id",
            "node1",
            "node2",
            "type",
            "w"
        ],
        "node_fields": [
            "id",
            "name",
            "type",
            "w"
        ],
        "without_nodes": false,
        "node1": "stylo",
        "#relations": 37,
        "max_relation_weight": 618.0,
        "#nodes": 38,
        "duration": "0:00:00.013005"
    }
}