{
    "nodes": [
        {
            "id": 14939886,
            "name": "en:gemstone",
            "type": 1,
            "w": 25
        },
        {
            "id": 15422466,
            "name": "en:semi-precious stone",
            "type": 1,
            "w": 25
        },
        {
            "id": 5812592,
            "name": "forme dérivée du cristal",
            "type": 1,
            "w": 25
        },
        {
            "id": 367263,
            "name": "oiseau passereau",
            "type": 1,
            "w": 50
        },
        {
            "id": 109624,
            "name": "stable",
            "type": 1,
            "w": 2891
        },
        {
            "id": 249619,
            "name": "matière minérale",
            "type": 1,
            "w": 80
        },
        {
            "id": 3325295,
            "name": "grain de",
            "type": 777,
            "w": 25
        },
        {
            "id": 85794,
            "name": "diamant",
            "type": 1,
            "w": 686
        },
        {
            "id": 15292120,
            "name": "en:a touch of",
            "type": 1,
            "w": 25
        },
        {
            "id": 401420678,
            "name": "pièce cornée",
            "type": 1,
            "w": 0
        },
        {
            "id": 13995234,
            "name": "allotrope de haute pression du carbone",
            "type": 1,
            "w": 25
        },
        {
            "id": 147238629,
            "name": "Pierre fine",
            "type": 1,
            "w": 34
        },
        {
            "id": 3224813,
            "name": "animal volant",
            "type": 1,
            "w": 4
        },
        {
            "id": 7095246,
            "name": "en:amniota",
            "type": 1,
            "w": 25
        },
        {
            "id": 325657,
            "name": "animal>117095>325656",
            "type": 1,
            "w": 74
        },
        {
            "id": 15781381,
            "name": "vrai métazoaire",
            "type": 1,
            "w": 2
        },
        {
            "id": 25008,
            "name": "pierre",
            "type": 1,
            "w": 9678
        },
        {
            "id": 14940408,
            "name": "en:gnathostome",
            "type": 1,
            "w": 25
        },
        {
            "id": 391010,
            "name": "coelomé",
            "type": 1,
            "w": 51
        },
        {
            "id": 265004,
            "name": "animal à sang chaud",
            "type": 1,
            "w": 6
        },
        {
            "id": 326373,
            "name": "sauropsidien",
            "type": 1,
            "w": 52
        },
        {
            "id": 264908,
            "name": "eumétazoaire",
            "type": 1,
            "w": 95
        },
        {
            "id": 15287364,
            "name": "en:metazoon",
            "type": 1,
            "w": 25
        },
        {
            "id": 12321907,
            "name": "en:eukaryote",
            "type": 1,
            "w": 25
        },
        {
            "id": 1483990,
            "name": "être vivant non humain",
            "type": 1,
            "w": 8
        },
        {
            "id": 87789,
            "name": "coelomate",
            "type": 1,
            "w": 56
        },
        {
            "id": 265838,
            "name": "archosaurien",
            "type": 1,
            "w": 52
        },
        {
            "id": 396042,
            "name": "tétrapode>86640",
            "type": 1,
            "w": 50
        },
        {
            "id": 142602,
            "name": "cordé",
            "type": 1,
            "w": 122
        },
        {
            "id": 101689,
            "name": "être animé",
            "type": 1,
            "w": 85
        },
        {
            "id": 1655534,
            "name": "c&oelig;lomate",
            "type": 1,
            "w": 25
        },
        {
            "id": 54794,
            "name": "eucaryote",
            "type": 1,
            "w": 268
        },
        {
            "id": 391009,
            "name": "célomate",
            "type": 1,
            "w": 50
        },
        {
            "id": 2461482,
            "name": "métazoaire supérieur",
            "type": 1,
            "w": 2
        },
        {
            "id": 265277,
            "name": "crâniate",
            "type": 1,
            "w": 70
        },
        {
            "id": 265220,
            "name": "épineurien",
            "type": 1,
            "w": 32
        },
        {
            "id": 143762329,
            "name": "Organisme vivant",
            "type": 1,
            "w": 33
        },
        {
            "id": 264881,
            "name": "crânié",
            "type": 1,
            "w": 64
        },
        {
            "id": 65081,
            "name": "organisme vivant",
            "type": 1,
            "w": 264
        },
        {
            "id": 248081,
            "name": "chordé",
            "type": 1,
            "w": 238
        },
        {
            "id": 260820,
            "name": "entité vivante",
            "type": 1,
            "w": 96
        },
        {
            "id": 233133,
            "name": "animal>117095",
            "type": 1,
            "w": 953
        },
        {
            "id": 116477,
            "name": "personne",
            "type": 1,
            "w": 34213
        },
        {
            "id": 30843,
            "name": "outil",
            "type": 1,
            "w": 12262
        },
        {
            "id": 237445,
            "name": "être>68439",
            "type": 1,
            "w": 65
        },
        {
            "id": 325736,
            "name": "holozoaire",
            "type": 1,
            "w": 72
        },
        {
            "id": 264880,
            "name": "bilatérien",
            "type": 1,
            "w": 85
        },
        {
            "id": 283634,
            "name": "sauropside",
            "type": 777,
            "w": 43
        },
        {
            "id": 55823,
            "name": "métazoaire",
            "type": 1,
            "w": 212
        },
        {
            "id": 265837,
            "name": "sauropsidé",
            "type": 1,
            "w": 6
        },
        {
            "id": 220337,
            "name": "oiseau>17559",
            "type": 1,
            "w": 930
        },
        {
            "id": 325728,
            "name": "uniconte",
            "type": 1,
            "w": 62
        },
        {
            "id": 86490,
            "name": "minéral",
            "type": 1,
            "w": 1231
        },
        {
            "id": 436570,
            "name": "entité biologique",
            "type": 1,
            "w": 62
        },
        {
            "id": 157007,
            "name": "être>146885",
            "type": 1,
            "w": 55
        },
        {
            "id": 14049840,
            "name": "organisme vivant pluricellulaire",
            "type": 1,
            "w": 25
        },
        {
            "id": 71624,
            "name": "être vivant",
            "type": 1,
            "w": 2588
        },
        {
            "id": 29208,
            "name": "matière",
            "type": 1,
            "w": 9389
        },
        {
            "id": 14049831,
            "name": "organisme vivant pluricellulaire hétérotrophe",
            "type": 1,
            "w": 7
        },
        {
            "id": 14049844,
            "name": "organisme vivant hétérotrophe",
            "type": 1,
            "w": 26
        },
        {
            "id": 267642,
            "name": "organisme animal",
            "type": 1,
            "w": 7
        },
        {
            "id": 115304,
            "name": "deutérostomien",
            "type": 1,
            "w": 123
        },
        {
            "id": 329657,
            "name": "choano-organisme",
            "type": 1,
            "w": 66
        },
        {
            "id": 101018,
            "name": "gnathostome",
            "type": 1,
            "w": 96
        },
        {
            "id": 317929,
            "name": "olfactorien",
            "type": 1,
            "w": 48
        },
        {
            "id": 110773,
            "name": "amniote",
            "type": 1,
            "w": 94
        },
        {
            "id": 330964,
            "name": "cordé>117095",
            "type": 1,
            "w": 42
        },
        {
            "id": 325738,
            "name": "filozoaire",
            "type": 1,
            "w": 99
        },
        {
            "id": 96851,
            "name": "pièce",
            "type": 1,
            "w": 8445
        },
        {
            "id": 325741,
            "name": "choanobionte",
            "type": 1,
            "w": 93
        },
        {
            "id": 86640,
            "name": "vertébré",
            "type": 1,
            "w": 1075
        },
        {
            "id": 225847,
            "name": "organisme>71624",
            "type": 1,
            "w": 134
        },
        {
            "id": 13369,
            "name": "être",
            "type": 1,
            "w": 908369
        },
        {
            "id": 17559,
            "name": "animal",
            "type": 1,
            "w": 18619
        },
        {
            "id": 58768,
            "name": "organisme",
            "type": 1,
            "w": 5020
        },
        {
            "id": 325731,
            "name": "opisthoconte",
            "type": 1,
            "w": 100
        },
        {
            "id": 316850,
            "name": "entité physique",
            "type": 1,
            "w": 56
        },
        {
            "id": 234036,
            "name": "être vivant>123933",
            "type": 1,
            "w": 325
        },
        {
            "id": 91794,
            "name": "tétrapode",
            "type": 1,
            "w": 142
        },
        {
            "id": 140176,
            "name": "oiseau",
            "type": 1,
            "w": 11161
        },
        {
            "id": 2481815,
            "name": "allotrope",
            "type": 1,
            "w": 34
        },
        {
            "id": 16324756,
            "name": "Pierre précieuse",
            "type": 777,
            "w": 25
        },
        {
            "id": 40733,
            "name": "diapside",
            "type": 1,
            "w": 101
        },
        {
            "id": 6927452,
            "name": "en:mineral",
            "type": 1,
            "w": 25
        },
        {
            "id": 11358,
            "name": "substance",
            "type": 1,
            "w": 4567
        },
        {
            "id": 14606397,
            "name": "organisme hétérotrophe",
            "type": 1,
            "w": 2
        },
        {
            "id": 112155,
            "name": "minérale",
            "type": 1,
            "w": 132
        },
        {
            "id": 167169,
            "name": "pierre semi-précieuse",
            "type": 1,
            "w": 100
        },
        {
            "id": 11981108,
            "name": "en:songbird",
            "type": 1,
            "w": 25
        },
        {
            "id": 14954746,
            "name": "en:precious stone",
            "type": 1,
            "w": 25
        },
        {
            "id": 104214,
            "name": "polyèdre",
            "type": 1,
            "w": 343
        },
        {
            "id": 367256,
            "name": "oiseau chanteur",
            "type": 1,
            "w": 50
        },
        {
            "id": 257758,
            "name": "objet de luxe",
            "type": 1,
            "w": 71
        },
        {
            "id": 238303,
            "name": "objet précieux",
            "type": 1,
            "w": 59
        },
        {
            "id": 118990,
            "name": "pierre précieuse",
            "type": 1,
            "w": 336
        },
        {
            "id": 3245868,
            "name": "saurien>3245867",
            "type": 1,
            "w": 25
        },
        {
            "id": 81142,
            "name": "pierre fine",
            "type": 1,
            "w": 88
        }
    ],
    "relations": [
        {
            "id": 425198372,
            "node1": 85794,
            "node2": 11358,
            "type": 6,
            "w": 35.0
        },
        {
            "id": 604575939,
            "node1": 85794,
            "node2": 13369,
            "type": 6,
            "w": 32.0
        },
        {
            "id": 98282636,
            "node1": 85794,
            "node2": 17559,
            "type": 6,
            "w": 58.0
        },
        {
            "id": 9899080,
            "node1": 85794,
            "node2": 25008,
            "type": 6,
            "w": 111.0
        },
        {
            "id": 425199918,
            "node1": 85794,
            "node2": 29208,
            "type": 6,
            "w": 32.0
        },
        {
            "id": 11252298,
            "node1": 85794,
            "node2": 30843,
            "type": 6,
            "w": 117.0
        },
        {
            "id": 98282641,
            "node1": 85794,
            "node2": 40733,
            "type": 6,
            "w": 55.0
        },
        {
            "id": 98282649,
            "node1": 85794,
            "node2": 54794,
            "type": 6,
            "w": 55.0
        },
        {
            "id": 98282651,
            "node1": 85794,
            "node2": 55823,
            "type": 6,
            "w": 55.0
        },
        {
            "id": 604546372,
            "node1": 85794,
            "node2": 58768,
            "type": 6,
            "w": 27.0
        },
        {
            "id": 98282656,
            "node1": 85794,
            "node2": 65081,
            "type": 6,
            "w": 35.0
        },
        {
            "id": 98282658,
            "node1": 85794,
            "node2": 71624,
            "type": 6,
            "w": 35.0
        },
        {
            "id": 618849396,
            "node1": 85794,
            "node2": 81142,
            "type": 6,
            "w": 34.0
        },
        {
            "id": 108401552,
            "node1": 85794,
            "node2": 86490,
            "type": 6,
            "w": 31.0
        },
        {
            "id": 98282668,
            "node1": 85794,
            "node2": 86640,
            "type": 6,
            "w": 55.0
        },
        {
            "id": 98282669,
            "node1": 85794,
            "node2": 87789,
            "type": 6,
            "w": 39.0
        },
        {
            "id": 98282671,
            "node1": 85794,
            "node2": 91794,
            "type": 6,
            "w": 55.0
        },
        {
            "id": 110915199,
            "node1": 85794,
            "node2": 96851,
            "type": 6,
            "w": 30.0
        },
        {
            "id": 98282681,
            "node1": 85794,
            "node2": 101018,
            "type": 6,
            "w": 57.0
        },
        {
            "id": 314906809,
            "node1": 85794,
            "node2": 101689,
            "type": 6,
            "w": 34.0
        },
        {
            "id": 108396119,
            "node1": 85794,
            "node2": 104214,
            "type": 6,
            "w": 26.0
        },
        {
            "id": 374148743,
            "node1": 85794,
            "node2": 109624,
            "type": 6,
            "w": 46.0
        },
        {
            "id": 98282690,
            "node1": 85794,
            "node2": 110773,
            "type": 6,
            "w": 55.0
        },
        {
            "id": 595650963,
            "node1": 85794,
            "node2": 112155,
            "type": 6,
            "w": 35.0
        },
        {
            "id": 98282695,
            "node1": 85794,
            "node2": 115304,
            "type": 6,
            "w": 55.0
        },
        {
            "id": 696669774,
            "node1": 85794,
            "node2": 116477,
            "type": 6,
            "w": 51.0
        },
        {
            "id": 9904220,
            "node1": 85794,
            "node2": 118990,
            "type": 6,
            "w": 152.0
        },
        {
            "id": 98282712,
            "node1": 85794,
            "node2": 140176,
            "type": 6,
            "w": 66.0
        },
        {
            "id": 98282716,
            "node1": 85794,
            "node2": 142602,
            "type": 6,
            "w": 55.0
        },
        {
            "id": 604560670,
            "node1": 85794,
            "node2": 157007,
            "type": 6,
            "w": 28.0
        },
        {
            "id": 618849409,
            "node1": 85794,
            "node2": 167169,
            "type": 6,
            "w": 32.0
        },
        {
            "id": 98282736,
            "node1": 85794,
            "node2": 220337,
            "type": 6,
            "w": 55.0
        },
        {
            "id": 98282739,
            "node1": 85794,
            "node2": 225847,
            "type": 6,
            "w": 35.0
        },
        {
            "id": 98282743,
            "node1": 85794,
            "node2": 233133,
            "type": 6,
            "w": 55.0
        },
        {
            "id": 98282747,
            "node1": 85794,
            "node2": 234036,
            "type": 6,
            "w": 30.0
        },
        {
            "id": 98282749,
            "node1": 85794,
            "node2": 237445,
            "type": 6,
            "w": 30.0
        },
        {
            "id": 9909039,
            "node1": 85794,
            "node2": 238303,
            "type": 6,
            "w": 16.0
        },
        {
            "id": 98282757,
            "node1": 85794,
            "node2": 248081,
            "type": 6,
            "w": 55.0
        },
        {
            "id": 595651814,
            "node1": 85794,
            "node2": 249619,
            "type": 6,
            "w": 31.0
        },
        {
            "id": 9926885,
            "node1": 85794,
            "node2": 257758,
            "type": 6,
            "w": 22.0
        },
        {
            "id": 98282761,
            "node1": 85794,
            "node2": 260820,
            "type": 6,
            "w": 30.0
        },
        {
            "id": 98282763,
            "node1": 85794,
            "node2": 264880,
            "type": 6,
            "w": 55.0
        },
        {
            "id": 98282765,
            "node1": 85794,
            "node2": 264881,
            "type": 6,
            "w": 55.0
        },
        {
            "id": 98282767,
            "node1": 85794,
            "node2": 264908,
            "type": 6,
            "w": 55.0
        },
        {
            "id": 618185032,
            "node1": 85794,
            "node2": 265004,
            "type": 6,
            "w": 30.0
        },
        {
            "id": 98282769,
            "node1": 85794,
            "node2": 265220,
            "type": 6,
            "w": 56.0
        },
        {
            "id": 98282771,
            "node1": 85794,
            "node2": 265277,
            "type": 6,
            "w": 55.0
        },
        {
            "id": 98282773,
            "node1": 85794,
            "node2": 265837,
            "type": 6,
            "w": 55.0
        },
        {
            "id": 98282774,
            "node1": 85794,
            "node2": 265838,
            "type": 6,
            "w": 55.0
        },
        {
            "id": 98282775,
            "node1": 85794,
            "node2": 267642,
            "type": 6,
            "w": 43.0
        },
        {
            "id": 98282777,
            "node1": 85794,
            "node2": 283634,
            "type": 6,
            "w": 56.0
        },
        {
            "id": 98282778,
            "node1": 85794,
            "node2": 316850,
            "type": 6,
            "w": 29.0
        },
        {
            "id": 98282780,
            "node1": 85794,
            "node2": 317929,
            "type": 6,
            "w": 55.0
        },
        {
            "id": 1058990056,
            "node1": 85794,
            "node2": 325657,
            "type": 6,
            "w": 25.0
        },
        {
            "id": 98282782,
            "node1": 85794,
            "node2": 325728,
            "type": 6,
            "w": 55.0
        },
        {
            "id": 98282784,
            "node1": 85794,
            "node2": 325731,
            "type": 6,
            "w": 55.0
        },
        {
            "id": 98282786,
            "node1": 85794,
            "node2": 325736,
            "type": 6,
            "w": 55.0
        },
        {
            "id": 98282788,
            "node1": 85794,
            "node2": 325738,
            "type": 6,
            "w": 55.0
        },
        {
            "id": 98282790,
            "node1": 85794,
            "node2": 325741,
            "type": 6,
            "w": 55.0
        },
        {
            "id": 98282794,
            "node1": 85794,
            "node2": 326373,
            "type": 6,
            "w": 55.0
        },
        {
            "id": 98282796,
            "node1": 85794,
            "node2": 329657,
            "type": 6,
            "w": 55.0
        },
        {
            "id": 98282799,
            "node1": 85794,
            "node2": 330964,
            "type": 6,
            "w": 55.0
        },
        {
            "id": 187430913,
            "node1": 85794,
            "node2": 367256,
            "type": 6,
            "w": 42.0
        },
        {
            "id": 705134980,
            "node1": 85794,
            "node2": 367263,
            "type": 6,
            "w": 25.0
        },
        {
            "id": 98282801,
            "node1": 85794,
            "node2": 391009,
            "type": 6,
            "w": 41.0
        },
        {
            "id": 98282802,
            "node1": 85794,
            "node2": 391010,
            "type": 6,
            "w": 42.0
        },
        {
            "id": 98282803,
            "node1": 85794,
            "node2": 396042,
            "type": 6,
            "w": 58.0
        },
        {
            "id": 98282804,
            "node1": 85794,
            "node2": 436570,
            "type": 6,
            "w": 36.0
        },
        {
            "id": 98282806,
            "node1": 85794,
            "node2": 1483990,
            "type": 6,
            "w": 40.0
        },
        {
            "id": 479724724,
            "node1": 85794,
            "node2": 1655534,
            "type": 6,
            "w": 26.0
        },
        {
            "id": 383968865,
            "node1": 85794,
            "node2": 2461482,
            "type": 6,
            "w": 30.0
        },
        {
            "id": 212926821,
            "node1": 85794,
            "node2": 2481815,
            "type": 6,
            "w": 30.0
        },
        {
            "id": 429678775,
            "node1": 85794,
            "node2": 3224813,
            "type": 6,
            "w": 26.0
        },
        {
            "id": 1012113273,
            "node1": 85794,
            "node2": 3245868,
            "type": 6,
            "w": 25.0
        },
        {
            "id": 118861090,
            "node1": 85794,
            "node2": 3325295,
            "type": 6,
            "w": 30.0
        },
        {
            "id": 113327980,
            "node1": 85794,
            "node2": 5812592,
            "type": 6,
            "w": 29.0
        },
        {
            "id": 377125184,
            "node1": 85794,
            "node2": 6927452,
            "type": 6,
            "w": 32.0
        },
        {
            "id": 776090733,
            "node1": 85794,
            "node2": 7095246,
            "type": 6,
            "w": 25.0
        },
        {
            "id": 618859573,
            "node1": 85794,
            "node2": 11981108,
            "type": 6,
            "w": 34.0
        },
        {
            "id": 377374526,
            "node1": 85794,
            "node2": 12321907,
            "type": 6,
            "w": 28.0
        },
        {
            "id": 353037945,
            "node1": 85794,
            "node2": 13995234,
            "type": 6,
            "w": 41.0
        },
        {
            "id": 357097351,
            "node1": 85794,
            "node2": 14049831,
            "type": 6,
            "w": 32.0
        },
        {
            "id": 357262102,
            "node1": 85794,
            "node2": 14049840,
            "type": 6,
            "w": 30.0
        },
        {
            "id": 359475351,
            "node1": 85794,
            "node2": 14049844,
            "type": 6,
            "w": 27.0
        },
        {
            "id": 765911997,
            "node1": 85794,
            "node2": 14606397,
            "type": 6,
            "w": 25.0
        },
        {
            "id": 539526920,
            "node1": 85794,
            "node2": 14939886,
            "type": 6,
            "w": 32.0
        },
        {
            "id": 391393159,
            "node1": 85794,
            "node2": 14940408,
            "type": 6,
            "w": 29.0
        },
        {
            "id": 539527043,
            "node1": 85794,
            "node2": 14954746,
            "type": 6,
            "w": 29.0
        },
        {
            "id": 774991733,
            "node1": 85794,
            "node2": 15287364,
            "type": 6,
            "w": 26.0
        },
        {
            "id": 929222170,
            "node1": 85794,
            "node2": 15292120,
            "type": 6,
            "w": 20.0
        },
        {
            "id": 706009466,
            "node1": 85794,
            "node2": 15422466,
            "type": 6,
            "w": 25.0
        },
        {
            "id": 618863945,
            "node1": 85794,
            "node2": 15781381,
            "type": 6,
            "w": 32.0
        },
        {
            "id": 704675123,
            "node1": 85794,
            "node2": 16324756,
            "type": 6,
            "w": 25.0
        },
        {
            "id": 706100623,
            "node1": 85794,
            "node2": 143762329,
            "type": 6,
            "w": 25.0
        },
        {
            "id": 706299365,
            "node1": 85794,
            "node2": 147238629,
            "type": 6,
            "w": 25.0
        },
        {
            "id": 1071875880,
            "node1": 85794,
            "node2": 401420678,
            "type": 6,
            "w": 5.0
        }
    ],
    "request": {
        "types_ids": [
            6
        ],
        "not_types_ids": null,
        "min_weight": 1,
        "max_weight": null,
        "start": "2025-12-16T20:42:35.437700",
        "relation_fields": [
            "id",
            "node1",
            "node2",
            "type",
            "w"
        ],
        "node_fields": [
            "id",
            "name",
            "type",
            "w"
        ],
        "without_nodes": false,
        "node1": "diamant",
        "#relations": 96,
        "max_relation_weight": 152.0,
        "#nodes": 97,
        "duration": "0:00:00.030165"
    }
}